restack_integrations_toolhouse/__init__.py
restack_integrations_toolhouse/functions/send_email.py
restack_integrations_toolhouse/functions/summarize_website.py
restack_integrations_toolhouse/service.py
restack_integrations_toolhouse/task_queue.py
restack_integrations_toolhouse/utils/toolhouse_client.py
restack_integrations_toolhouse-0.0.3.dist-info/METADATA
restack_integrations_toolhouse-0.0.3.dist-info/WHEEL
restack_integrations_toolhouse-0.0.3.dist-info/RECORD
