Metadata-Version: 2.1
Name: restack_integrations_toolhouse
Version: 0.0.3
Summary: Toolhouse integration for Restack AI
Author: Restack Team
Author-email: service@restack.io
Requires-Python: >=3.10,<3.13
Classifier: Programming Language :: Python :: 3
Classifier: Programming Language :: Python :: 3.10
Classifier: Programming Language :: Python :: 3.11
Classifier: Programming Language :: Python :: 3.12
Requires-Dist: pydantic (>=2.9.2,<3.0.0)
Requires-Dist: restack_ai (>=0.0.11,<0.0.12)
Requires-Dist: toolhouse (>=1.3.0,<2.0.0)
